<filesystem>

    <folder name="QuickSearch">
        <folder name="EOPedia">
            <attr name="command" stringvalue="eopedia"/>
            <attr name="position" intvalue="0"/>
            <file name="org-eomasters-eopedia-SearchProvider.instance">
                <attr name="displayName" stringvalue="EOPedia"/>
            </file>
        </folder>
    </folder>


    <folder name="Services">
        <folder name="JavaHelp">
            <file name="org-eomasters-eopedia-helpset.xml" url="helpset.xml">
                <attr name="position" intvalue="1"/>
            </file>
        </folder>
    </folder>


</filesystem>